README.md
setup.py
make_taz/__init__.py
make_taz/segmentation.py
make_taz/simplify.py
make_taz.egg-info/PKG-INFO
make_taz.egg-info/SOURCES.txt
make_taz.egg-info/dependency_links.txt
make_taz.egg-info/not-zip-safe
make_taz.egg-info/top_level.txt
test/test.py