Metadata-Version: 1.0
Name: make-taz
Version: 0.1
Summary: implementation segmentation of urban areas using road network
Home-page: http://github.com/
Author: Haoming Zhuang
Author-email: csuhaoming@163.com
License: MIT
Platform: UNKNOWN
